<annotation>
	<folder></folder>
	<filename>000443_jpg.rf.7c253006be0ddc72ae7e98d5e040366f.jpg</filename>
	<path>000443_jpg.rf.7c253006be0ddc72ae7e98d5e040366f.jpg</path>
	<source>
		<database>roboflow.ai</database>
	</source>
	<size>
		<width>416</width>
		<height>416</height>
		<depth>3</depth>
	</size>
	<segmented>0</segmented>
	<object>
		<name>upright</name>
		<pose>Unspecified</pose>
		<truncated>0</truncated>
		<difficult>0</difficult>
		<occluded>0</occluded>
		<bndbox>
			<xmin>182</xmin>
			<xmax>297</xmax>
			<ymin>147</ymin>
			<ymax>382</ymax>
		</bndbox>
	</object>
</annotation>
