<annotation>
	<folder></folder>
	<filename>000979_jpg.rf.20dae38ff084d9d7b761d0630b9eda22.jpg</filename>
	<path>000979_jpg.rf.20dae38ff084d9d7b761d0630b9eda22.jpg</path>
	<source>
		<database>roboflow.ai</database>
	</source>
	<size>
		<width>416</width>
		<height>416</height>
		<depth>3</depth>
	</size>
	<segmented>0</segmented>
	<object>
		<name>upright</name>
		<pose>Unspecified</pose>
		<truncated>0</truncated>
		<difficult>0</difficult>
		<occluded>0</occluded>
		<bndbox>
			<xmin>149</xmin>
			<xmax>234</xmax>
			<ymin>180</ymin>
			<ymax>351</ymax>
		</bndbox>
	</object>
</annotation>
