<annotation>
	<folder></folder>
	<filename>001965_jpg.rf.1cab28da9df039681ad2b852c2fac3d2.jpg</filename>
	<path>001965_jpg.rf.1cab28da9df039681ad2b852c2fac3d2.jpg</path>
	<source>
		<database>roboflow.ai</database>
	</source>
	<size>
		<width>416</width>
		<height>416</height>
		<depth>3</depth>
	</size>
	<segmented>0</segmented>
	<object>
		<name>upright</name>
		<pose>Unspecified</pose>
		<truncated>0</truncated>
		<difficult>0</difficult>
		<occluded>0</occluded>
		<bndbox>
			<xmin>161</xmin>
			<xmax>251</xmax>
			<ymin>126</ymin>
			<ymax>374</ymax>
		</bndbox>
	</object>
</annotation>
