<annotation>
	<folder></folder>
	<filename>002778_jpg.rf.6dffd21b9aa973b55f86837000e804d9.jpg</filename>
	<path>002778_jpg.rf.6dffd21b9aa973b55f86837000e804d9.jpg</path>
	<source>
		<database>roboflow.ai</database>
	</source>
	<size>
		<width>416</width>
		<height>416</height>
		<depth>3</depth>
	</size>
	<segmented>0</segmented>
	<object>
		<name>fall</name>
		<pose>Unspecified</pose>
		<truncated>0</truncated>
		<difficult>0</difficult>
		<occluded>0</occluded>
		<bndbox>
			<xmin>147</xmin>
			<xmax>273</xmax>
			<ymin>212</ymin>
			<ymax>367</ymax>
		</bndbox>
	</object>
</annotation>
